odoo/addons/sale_order_type/README.rst
odoo/addons/sale_order_type/__init__.py
odoo/addons/sale_order_type/__manifest__.py
odoo/addons/sale_order_type/data/default_type.xml
odoo/addons/sale_order_type/demo/sale_order_demo.xml
odoo/addons/sale_order_type/i18n/am.po
odoo/addons/sale_order_type/i18n/ar.po
odoo/addons/sale_order_type/i18n/bg.po
odoo/addons/sale_order_type/i18n/bs.po
odoo/addons/sale_order_type/i18n/ca.po
odoo/addons/sale_order_type/i18n/ca_ES.po
odoo/addons/sale_order_type/i18n/cs.po
odoo/addons/sale_order_type/i18n/da.po
odoo/addons/sale_order_type/i18n/de.po
odoo/addons/sale_order_type/i18n/el_GR.po
odoo/addons/sale_order_type/i18n/en_GB.po
odoo/addons/sale_order_type/i18n/es.po
odoo/addons/sale_order_type/i18n/es_AR.po
odoo/addons/sale_order_type/i18n/es_CL.po
odoo/addons/sale_order_type/i18n/es_CO.po
odoo/addons/sale_order_type/i18n/es_CR.po
odoo/addons/sale_order_type/i18n/es_DO.po
odoo/addons/sale_order_type/i18n/es_EC.po
odoo/addons/sale_order_type/i18n/es_ES.po
odoo/addons/sale_order_type/i18n/es_MX.po
odoo/addons/sale_order_type/i18n/es_PE.po
odoo/addons/sale_order_type/i18n/es_PY.po
odoo/addons/sale_order_type/i18n/es_VE.po
odoo/addons/sale_order_type/i18n/et.po
odoo/addons/sale_order_type/i18n/eu.po
odoo/addons/sale_order_type/i18n/fa.po
odoo/addons/sale_order_type/i18n/fi.po
odoo/addons/sale_order_type/i18n/fr.po
odoo/addons/sale_order_type/i18n/fr_CA.po
odoo/addons/sale_order_type/i18n/fr_CH.po
odoo/addons/sale_order_type/i18n/fr_FR.po
odoo/addons/sale_order_type/i18n/gl.po
odoo/addons/sale_order_type/i18n/gl_ES.po
odoo/addons/sale_order_type/i18n/he.po
odoo/addons/sale_order_type/i18n/hr.po
odoo/addons/sale_order_type/i18n/hr_HR.po
odoo/addons/sale_order_type/i18n/hu.po
odoo/addons/sale_order_type/i18n/id.po
odoo/addons/sale_order_type/i18n/it.po
odoo/addons/sale_order_type/i18n/ja.po
odoo/addons/sale_order_type/i18n/ko.po
odoo/addons/sale_order_type/i18n/lt.po
odoo/addons/sale_order_type/i18n/lt_LT.po
odoo_addon_sale_order_type-19.0.1.0.0.2.dist-info/METADATA
odoo_addon_sale_order_type-19.0.1.0.0.2.dist-info/WHEEL
odoo_addon_sale_order_type-19.0.1.0.0.2.dist-info/top_level.txt
odoo_addon_sale_order_type-19.0.1.0.0.2.dist-info/RECORD
